ch_tools/__init__.py
ch_tools/chadmin/README.md
ch_tools/chadmin/__init__.py
ch_tools/chadmin/chadmin_cli.py
ch_tools/chadmin/cli/__init__.py
ch_tools/chadmin/cli/chs3_backup_group.py
ch_tools/chadmin/cli/config_command.py
ch_tools/chadmin/cli/crash_log_group.py
ch_tools/chadmin/cli/data_store_group.py
ch_tools/chadmin/cli/database_group.py
ch_tools/chadmin/cli/diagnostics_command.py
ch_tools/chadmin/cli/dictionary_group.py
ch_tools/chadmin/cli/disk_group.py
ch_tools/chadmin/cli/list_async_metrics_command.py
ch_tools/chadmin/cli/list_events_command.py
ch_tools/chadmin/cli/list_functions_command.py
ch_tools/chadmin/cli/list_macros_command.py
ch_tools/chadmin/cli/list_metrics_command.py
ch_tools/chadmin/cli/list_settings_command.py
ch_tools/chadmin/cli/merge_group.py
ch_tools/chadmin/cli/mutation_group.py
ch_tools/chadmin/cli/object_storage_group.py
ch_tools/chadmin/cli/part_group.py
ch_tools/chadmin/cli/part_log_group.py
ch_tools/chadmin/cli/partition_group.py
ch_tools/chadmin/cli/process_group.py
ch_tools/chadmin/cli/query_log_group.py
ch_tools/chadmin/cli/replicated_fetch_group.py
ch_tools/chadmin/cli/replication_queue_group.py
ch_tools/chadmin/cli/restore_replica_command.py
ch_tools/chadmin/cli/stack_trace_command.py
ch_tools/chadmin/cli/table_group.py
ch_tools/chadmin/cli/table_replica_group.py
ch_tools/chadmin/cli/thread_log_group.py
ch_tools/chadmin/cli/wait_started_command.py
ch_tools/chadmin/cli/zookeeper_group.py
ch_tools/chadmin/internal/__init__.py
ch_tools/chadmin/internal/backup.py
ch_tools/chadmin/internal/diagnostics/__init__.py
ch_tools/chadmin/internal/diagnostics/data.py
ch_tools/chadmin/internal/diagnostics/diagnose.py
ch_tools/chadmin/internal/diagnostics/formatter.py
ch_tools/chadmin/internal/diagnostics/query.py
ch_tools/chadmin/internal/diagnostics/utils.py
ch_tools/chadmin/internal/dictionary.py
ch_tools/chadmin/internal/object_storage/__init__.py
ch_tools/chadmin/internal/object_storage/collect_metadata.py
clickhouse_tools-2.1.71613250.dist-info/entry_points.txt
clickhouse_tools-2.1.71613250.dist-info/LICENSE
clickhouse_tools-2.1.71613250.dist-info/WHEEL
clickhouse_tools-2.1.71613250.dist-info/METADATA
clickhouse_tools-2.1.71613250.dist-info/RECORD
