Metadata-Version: 2.1
Name: clickhouse-tools
Version: 2.1.71613250
Summary: clickhouse-tools is a set of tools for administration and diagnostics of ClickHouse DBMS.
Home-page: https://github.com/yandex/ch-tools
License: MIT
Keywords: clickhouse,database,monitoring,diagnostics,administration
Author: Alexander Burmak
Author-email: alex-burmak@yandex-team.ru
Maintainer: Alexander Burmak
Maintainer-email: alex-burmak@yandex-team.ru
Requires-Python: >=3.6.2,<4.0.0
Classifier: Development Status :: 5 - Production/Stable
Classifier: Environment :: Console
Classifier: Intended Audience :: Developers
Classifier: Intended Audience :: System Administrators
Classifier: License :: OSI Approved :: MIT License
Classifier: Operating System :: MacOS
Classifier: Operating System :: POSIX :: BSD
Classifier: Operating System :: POSIX :: Linux
Classifier: Operating System :: Unix
Classifier: Programming Language :: Python :: 3
Classifier: Programming Language :: Python :: 3.10
Classifier: Programming Language :: Python :: 3.11
Classifier: Programming Language :: Python :: 3.12
Classifier: Programming Language :: Python :: 3.6
Classifier: Programming Language :: Python :: 3.7
Classifier: Programming Language :: Python :: 3.8
Classifier: Programming Language :: Python :: 3.9
Classifier: Topic :: Database
Classifier: Typing :: Typed
Requires-Dist: boto3 (>=1.23.10,<1.24.0)
Requires-Dist: click (>=8.0.4,<8.1.0)
Requires-Dist: cloup
Requires-Dist: deepdiff
Requires-Dist: dnspython
Requires-Dist: file_read_backwards
Requires-Dist: humanfriendly
Requires-Dist: jinja2
Requires-Dist: kazoo
Requires-Dist: lxml
Requires-Dist: psutil
Requires-Dist: pygments
Requires-Dist: pyopenssl
Requires-Dist: python-dateutil
Requires-Dist: pyyaml (<5.4)
Requires-Dist: requests
Requires-Dist: tabulate
Requires-Dist: tenacity
Requires-Dist: termcolor
Requires-Dist: tqdm
Requires-Dist: typing-extensions (>=4.1.1,<4.2.0)
Requires-Dist: xmltodict
Project-URL: Repository, https://github.com/yandex/ch-tools
